item_matching/README.md
item_matching/__init__.py
item_matching/main_match.py
item_matching/func/function_image.py
item_matching/func/function_text.py
item_matching/func/post_processing.py
item_matching/pipeline/build_index_and_query.py
item_matching/pipeline/data_loading.py
item_matching/pipeline/func.py
item_matching/pipeline/rerank.py
item_matching-0.0.108.dist-info/METADATA
item_matching-0.0.108.dist-info/WHEEL
item_matching-0.0.108.dist-info/licenses/LICENSE
item_matching-0.0.108.dist-info/RECORD
