Metadata-Version: 2.4
Name: item_matching
Version: 0.0.108
Summary: A name matching package
Project-URL: Homepage, https://github.com/kevinkhang2909/item_matching
Project-URL: Bug Tracker, https://github.com/kevinkhang2909/item_matching/issues
Author-email: Kevin Khang <kevinkhang2909@gmail.com>
License: Copyright (c) 2024 Kevin Khang
License-File: LICENSE
Keywords: semantic, retrieval
Classifier: License :: OSI Approved :: MIT License
Classifier: Operating System :: OS Independent
Classifier: Programming Language :: Python :: 3
Requires-Python: >=3.11
Requires-Dist: albumentations
Requires-Dist: autofaiss
Requires-Dist: datasets
Requires-Dist: duckdb
Requires-Dist: einops
Requires-Dist: emoji
Requires-Dist: flagembedding
Requires-Dist: matplotlib
Requires-Dist: peft
Requires-Dist: polars
Requires-Dist: pyarrow
Requires-Dist: scikit-learn
Requires-Dist: sentencepiece
Requires-Dist: torch
Requires-Dist: torchvision
Requires-Dist: transformers
